aioruckus/__init__.py
aioruckus/abcsession.py
aioruckus/ajaxsession.py
aioruckus/backupsession.py
aioruckus/const.py
aioruckus/exceptions.py
aioruckus/r1ajaxapi.py
aioruckus/ruckusajaxapi.py
aioruckus/ruckusapi.py
aioruckus/ruckusbackupapi.py
aioruckus/smartzoneajaxapi.py
aioruckus/typing_policy.py
aioruckus-0.42.dist-info/LICENSE
aioruckus-0.42.dist-info/METADATA
aioruckus-0.42.dist-info/WHEEL
aioruckus-0.42.dist-info/top_level.txt
aioruckus-0.42.dist-info/RECORD
