Metadata-Version: 2.1
Name: aioruckus
Version: 0.42
Summary: Python API to interact with Ruckus Unleashed and ZoneDirector devices.
Home-page: https://github.com/ms264556/aioruckus
Author: ms264556
Author-email: bsd0@patterni.city
License: BSD0
Classifier: Programming Language :: Python :: 3
Classifier: License :: OSI Approved :: BSD License
Classifier: Operating System :: OS Independent
Requires-Python: >=3.10
License-File: LICENSE
Requires-Dist: aiohttp>=3.8.4
Requires-Dist: xmltodict>=0.13.0
Requires-Dist: cryptography>=41.0.0
